ciare_world_creator/__init__.py
ciare_world_creator/cli.py
ciare_world_creator/collections/utils.py
ciare_world_creator/commands/__init__.py
ciare_world_creator/commands/create.py
ciare_world_creator/commands/fix.py
ciare_world_creator/commands/list.py
ciare_world_creator/commands/purge.py
ciare_world_creator/contexts_prompts/__init__.py
ciare_world_creator/contexts_prompts/edit.py
ciare_world_creator/contexts_prompts/model.py
ciare_world_creator/contexts_prompts/place.py
ciare_world_creator/contexts_prompts/world.py
ciare_world_creator/llm/__init__.py
ciare_world_creator/llm/model.py
ciare_world_creator/model_databases/__init__.py
ciare_world_creator/model_databases/fetch_models.py
ciare_world_creator/model_databases/fetch_worlds.py
ciare_world_creator/model_databases/gazebo.py
ciare_world_creator/utils/__init__.py
ciare_world_creator/utils/cache.py
ciare_world_creator/utils/json.py
ciare_world_creator/utils/style.py
ciare_world_creator/xml/__init__.py
ciare_world_creator/xml/empty_world.py
ciare_world_creator/xml/worlds.py
ciare_world_creator-0.1.2.dist-info/entry_points.txt
ciare_world_creator-0.1.2.dist-info/LICENSE.md
ciare_world_creator-0.1.2.dist-info/WHEEL
ciare_world_creator-0.1.2.dist-info/METADATA
ciare_world_creator-0.1.2.dist-info/RECORD
