Metadata-Version: 2.1
Name: ciare-world-creator
Version: 0.1.2
Summary: 
Author: Alex Karavaev
Author-email: alexkaravaev@alexkaravaev.xyz
Requires-Python: >=3.8.1,<3.11
Classifier: Programming Language :: Python :: 3
Classifier: Programming Language :: Python :: 3.10
Classifier: Programming Language :: Python :: 3.9
Requires-Dist: aiohttp (>=3.8.4,<4.0.0)
Requires-Dist: asyncio (>=3.4.3,<4.0.0)
Requires-Dist: chromadb (>=0.3.26,<0.4.0)
Requires-Dist: click (>=8.1.3,<9.0.0)
Requires-Dist: langchain (>=0.0.222,<0.0.223)
Requires-Dist: lark (>=1.1.5,<2.0.0)
Requires-Dist: lxml (>=4.9.2,<5.0.0)
Requires-Dist: openai (>=0.27.8,<0.28.0)
Requires-Dist: pandas (>=2.0.3,<3.0.0)
Requires-Dist: pre-commit (>=3.3.3,<4.0.0)
Requires-Dist: questionary (>=1.10.0,<2.0.0)
Requires-Dist: tabulate (>=0.9.0,<0.10.0)
Requires-Dist: tinydb (>=4.8.0,<5.0.0)
Requires-Dist: tqdm (>=4.65.0,<5.0.0)
